pydemic/__init__.py
pydemic/_git_rev.py
pydemic/desolver.py
pydemic/distributions.py
pydemic/hdf.py
pydemic/mitigation.py
pydemic/reactions.py
pydemic/sampling.py
pydemic/simulation.py
pydemic/data/__init__.py
pydemic/data/united_states.py
pydemic/models/__init__.py
pydemic/models/seir.py
pydemic/models/seirpp.py
pydemic-2020.2.2.dist-info/LICENSE
pydemic-2020.2.2.dist-info/METADATA
pydemic-2020.2.2.dist-info/WHEEL
pydemic-2020.2.2.dist-info/top_level.txt
pydemic-2020.2.2.dist-info/RECORD
