Metadata-Version: 2.1
Name: pydemic
Version: 2020.2.2
Summary: A python driver for epidemic modeling and inference
Home-page: https://github.com/uiuc-covid19-modeling/pydemic
Author: Zachary J Weiner, George N Wong
License: MIT
Project-URL: Documentation, https://pydemic.readthedocs.io/en/latest/
Project-URL: Source, https://github.com/uiuc-covid19-modeling/pydemic
Platform: UNKNOWN
Classifier: Development Status :: 4 - Beta
Classifier: Intended Audience :: Science/Research
Classifier: License :: OSI Approved :: MIT License
Classifier: Programming Language :: Python :: 3
Requires-Python: >=3
Requires-Dist: numpy
Requires-Dist: scipy
Requires-Dist: pandas
Requires-Dist: emcee
Requires-Dist: h5py
Requires-Dist: tables
